linear_reg/__init__.py
linear_reg/main.py
linear_reg/simple_linear_regr.py
linear_reg/simple_linear_regr_utils.py
simp2-0.0.1.dist-info/LICENSE
simp2-0.0.1.dist-info/METADATA
simp2-0.0.1.dist-info/WHEEL
simp2-0.0.1.dist-info/top_level.txt
simp2-0.0.1.dist-info/RECORD
